clever_chat/__init__.py
clever_chat/clever.py
clever_chat-1.0.1.dist-info/METADATA
clever_chat-1.0.1.dist-info/WHEEL
clever_chat-1.0.1.dist-info/top_level.txt
clever_chat-1.0.1.dist-info/RECORD
