Metadata-Version: 2.1
Name: clever-chat
Version: 1.0.1
Summary: An API Wrapper for clever-chat (chatbot) in Python
Home-page: https://github.com/XPr0methiumX/Clever-chat
Author: Pr0methium
License: MIT
Keywords: python,chatbot,chat
Platform: UNKNOWN
Classifier: Development Status :: 5 - Production/Stable
Classifier: Intended Audience :: Developers
Classifier: Programming Language :: Python :: 3
Classifier: Operating System :: OS Independent
Requires-Dist: aiohttp
Requires-Dist: requests
